dkdc_email/__init__.py
dkdc_email/gmail.py
dkdc_email-0.0.1.dist-info/METADATA
dkdc_email-0.0.1.dist-info/WHEEL
dkdc_email-0.0.1.dist-info/top_level.txt
dkdc_email-0.0.1.dist-info/RECORD
